CHANGELOG.txt
LICENCE.txt
MANIFEST.in
README.txt
setup.py
Wiki_Calculator.egg-info/PKG-INFO
Wiki_Calculator.egg-info/SOURCES.txt
Wiki_Calculator.egg-info/dependency_links.txt
Wiki_Calculator.egg-info/top_level.txt
wiki_basic_calculator/__init__.py