Metadata-Version: 2.1
Name: Wiki-Calculator
Version: 0.0.1
Summary: Simple calculator for adding, subtracting, multiplying and dividing two numbers
Home-page: UNKNOWN
Author: Wycliffe Oloo
Author-email: wycliflocka@gmail.com
License: MIT
Keywords: calculator
Platform: UNKNOWN
Classifier: Development Status :: 5 - Production/Stable
Classifier: Intended Audience :: Education
Classifier: Operating System :: Microsoft :: Windows :: Windows 10
Classifier: License :: OSI Approved :: MIT License
Classifier: Programming Language :: Python :: 3
License-File: LICENCE.txt
